async_task_helpers/__init__.py
async_task_helpers/async_callback_handler.py
async_task_helpers/async_loop_task.py
async_task_helpers/type_hint.py
async_task_helpers-1.0.1.dist-info/METADATA
async_task_helpers-1.0.1.dist-info/WHEEL
async_task_helpers-1.0.1.dist-info/top_level.txt
async_task_helpers-1.0.1.dist-info/RECORD
