Metadata-Version: 2.1
Name: async-task-helpers
Version: 1.0.1
Summary: Simple asynchronous task helpers
Home-page: https://github.com/Lapis0875/async_task_helpers
Author: Lapis0875
Author-email: lapis0875@kakao.com
License: MIT
Project-URL: Issue tracker, https://github.com/Lapis0875/async_task_helpers/issues
Project-URL: Donate, https://www.patreon.com/lapis0875
Keywords: asyncio,task,loop task
Platform: UNKNOWN
Classifier: Programming Language :: Python :: 3.7
Classifier: Programming Language :: Python :: 3.8
Classifier: Programming Language :: Python :: 3.9
Classifier: License :: OSI Approved :: MIT License
Classifier: Operating System :: OS Independent
Classifier: Topic :: Software Development :: Libraries
Classifier: Topic :: Software Development :: Libraries :: Python Modules
Requires-Python: >=3.7.0
